{
  "db_name": "PostgreSQL",
  "query": "SELECT pub_id, name, email FROM users",
  "describe": {
    "columns": [
      {
        "ordinal": 0,
        "name": "pub_id",
        "type_info": "Varchar"
      },
      {
        "ordinal": 1,
        "name": "name",
        "type_info": "Varchar"
      },
      {
        "ordinal": 2,
        "name": "email",
        "type_info": {
          "Custom": {
            "name": "citext",
            "kind": "Simple"
          }
        }
      }
    ],
    "parameters": {
      "Left": []
    },
    "nullable": [
      false,
      false,
      false
    ]
  },
  "hash": "aa67ad90796003f28217044e93dd3813b4cb1e451c901f3f3002d37f9baed979"
}
